pycord_cogsbyserver/__init__.py
pycord_cogsbyserver/_servercog.py
pycord_cogsbyserver/_utils.py
pycord_cogsbyserver-0.3.2.dist-info/WHEEL
pycord_cogsbyserver-0.3.2.dist-info/METADATA
pycord_cogsbyserver-0.3.2.dist-info/RECORD
