Metadata-Version: 2.1
Name: pycord-cogsbyserver
Version: 0.3.2
Summary: A pycord extension that adds cogs that have a different object for each server.
Home-page: https://github.com/NathanNull/pycord-cogsbyserver
License: MIT
Author: Nathan Strong
Author-email: nathanstrong777@gmail.com
Requires-Python: >=3.10,<4.0
Classifier: License :: OSI Approved :: MIT License
Classifier: Programming Language :: Python :: 3
Classifier: Programming Language :: Python :: 3.10
Requires-Dist: py-cord (>=2.1.3,<3.0.0)
Project-URL: Repository, https://github.com/NathanNull/pycord-cogsbyserver
